pyinit/__init__.py
pyinit/__main__.py
pyinit/templates/__init__.py
pyinit/templates/data_management.py.tpl
pyinit/templates/env.tpl
pyinit/templates/mailosaur_configuration.py.tpl
pyinit/templates/project_configuration.py.tpl
pyinitpro-0.1.15.dist-info/METADATA
pyinitpro-0.1.15.dist-info/WHEEL
pyinitpro-0.1.15.dist-info/entry_points.txt
pyinitpro-0.1.15.dist-info/top_level.txt
pyinitpro-0.1.15.dist-info/RECORD
