Metadata-Version: 2.1
Name: pyinitpro
Version: 0.1.15
Summary: A CLI tool to scaffold Python projects with venv and folder structure
Home-page: https://github.com/Martins-O/pyinit.git
Author: Martins O Jojolola
License: MIT
Project-URL: Source, https://github.com/Martins-O/pyinit
Project-URL: Tracker, https://github.com/Martins-O/pyinit/issues
Keywords: python cli scaffold virtualenv project setup
Platform: UNKNOWN
Classifier: Programming Language :: Python :: 3
Classifier: Operating System :: OS Independent
Requires-Python: >=3.9
Requires-Dist: colorama>=0.4.0
